root_optimize/__init__.py
root_optimize/commandline.py
root_optimize/json.py
root_optimize/plotting.py
root_optimize/timing.py
root_optimize/utils.py
root_optimize/version.py
root_optimize-0.8.5.dist-info/LICENSE
root_optimize-0.8.5.dist-info/METADATA
root_optimize-0.8.5.dist-info/WHEEL
root_optimize-0.8.5.dist-info/entry_points.txt
root_optimize-0.8.5.dist-info/top_level.txt
root_optimize-0.8.5.dist-info/RECORD
